Metadata-Version: 2.1
Name: dbml-to-sqlalchemy
Version: 0.9.2
Summary: dbml-to-sqlalchemy extension for sqlachemy: upload dbml model in orm sqlalchemy
Home-page: https://github.com/fraoustin/dbml-to-sqlalchemy.git
Author: Frédéric Aoustin
Author-email: fraoustin@gmail.com
License: UNKNOWN
Platform: any
Classifier: Programming Language :: Python
Classifier: License :: OSI Approved :: GNU General Public License v2 (GPLv2)
Classifier: Operating System :: OS Independent
Classifier: Programming Language :: Python :: 3
Classifier: Programming Language :: Python :: 3.7
Classifier: Programming Language :: Python :: 3.8
Classifier: Programming Language :: Python :: 3.9
Classifier: Programming Language :: Python :: 3.10
Classifier: Programming Language :: Python :: 3.11
Classifier: Topic :: Software Development :: Libraries :: Python Modules
Classifier: Environment :: Web Environment
License-File: AUTHORS.txt
